[
 {
  "sid":"Main_Sim:593:76:1:92:80",
  "className":"Simulink.Outport",
  "icon":"WebViewIcon3",
  "name":"phi",
  "label":"phi",
  "parent":"Main_Sim:593:76:1:92:36",
  "inspector":{
   "params":[
    "Port",
    "IconDisplay",
    "OutMin",
    "OutMax",
    "OutDataTypeStr",
    "LockScale",
    "Unit",
    "PortDimensions",
    "VarSizeSig",
    "SampleTime",
    "SignalType",
    "BusOutputAsStruct",
    "EnsureOutportIsVirtual",
    "InitialOutput",
    "MustResolveToSignalObject",
    "OutputWhenDisabled",
    "OutputWhenUnConnected",
    "OutputWhenUnconnectedValue",
    "SignalName",
    "SignalObject",
    "SourceOfInitialOutputValue",
    "StorageClass",
    "VectorParamsAs1DForOutWhenUnconnected"
   ],
   "values":[
    "1",
    "Port number",
    "[]",
    "[]",
    "Inherit: auto",
    "off",
    "inherit",
    "-1",
    "Inherit",
    "-1",
    "auto",
    "off",
    "off",
    "0",
    "off",
    "held",
    "off",
    "0",
    "",
    [
    ],
    "Dialog",
    "Auto",
    "off"
   ],
   "tabs":[
    "Main",
    "Signal Attributes",
    "-Other"
   ],
   "tabs_idx":[
    0,
    2,
    11
   ]
  },
  "viewer":{
   "jshandler":"webview/handlers/ElementHandler"
  },
  "obj_viewer":[
  ],
  "finder":{
   "blocktype":"Outport",
   "masktype":""
  }
 },
 {
  "sid":"Main_Sim:593:76:1:92:79",
  "className":"Simulink.InportShadow",
  "icon":"WebViewIcon3",
  "name":"rho ",
  "label":"rho ",
  "parent":"Main_Sim:593:76:1:92:36",
  "inspector":{
   "params":[
    "Port",
    "IconDisplay",
    "LatchByDelayingOutsideSignal",
    "LatchInputForFeedbackSignals",
    "OutputFunctionCall",
    "OutMin",
    "OutMax",
    "OutDataTypeStr",
    "LockScale",
    "Unit",
    "PortDimensions",
    "VarSizeSig",
    "SampleTime",
    "SignalType",
    "BusOutputAsStruct",
    "Element",
    "InputConnect",
    "Interpolate",
    "IsBusElementPort",
    "PortName"
   ],
   "values":[
    "1",
    "Port number",
    "off",
    "off",
    "off",
    "[]",
    "[]",
    "Inherit: auto",
    "off",
    "inherit",
    "-1",
    "Inherit",
    "-1",
    "auto",
    "off",
    "",
    "",
    "on",
    "off",
    "rho"
   ],
   "tabs":[
    "Main",
    "Signal Attributes",
    "-Other"
   ],
   "tabs_idx":[
    0,
    4,
    14
   ]
  },
  "viewer":{
   "jshandler":"webview/handlers/ElementHandler"
  },
  "obj_viewer":[
  ],
  "finder":{
   "blocktype":"InportShadow",
   "masktype":""
  }
 },
 {
  "sid":"Main_Sim:593:76:1:92:78",
  "className":"Simulink.WhileIterator",
  "icon":"WebViewIcon3",
  "name":"While Iterator",
  "label":"While Iterator",
  "parent":"Main_Sim:593:76:1:92:36",
  "inspector":{
   "params":[
    "MaxIters",
    "WhileBlockType",
    "ResetStates",
    "ShowIterationPort",
    "OutputDataType"
   ],
   "values":[
    "5",
    "do-while",
    "held",
    "on",
    "int8"
   ],
   "tabs":[
    "Parameter Attributes"
   ],
   "tabs_idx":0
  },
  "viewer":{
   "jshandler":"webview/handlers/ElementHandler"
  },
  "obj_viewer":[
  ],
  "finder":{
   "blocktype":"WhileIterator",
   "masktype":""
  }
 },
 {
  "sid":"Main_Sim:593:76:1:92:67",
  "className":"Simulink.SubSystem",
  "icon":"WebViewIcon1",
  "name":"Subsystem4",
  "label":"Subsystem4",
  "parent":"Main_Sim:593:76:1:92:36",
  "inspector":{
   "params":[
    "ShowPortLabels",
    "Permissions",
    "ErrorFcn",
    "PermitHierarchicalResolution",
    "TreatAsAtomicUnit",
    "MinAlgLoopOccurrences",
    "SystemSampleTime",
    "TreatAsGroupedWhenPropagatingVariantConditions",
    "RTWSystemCode",
    "RTWFcnNameOpts",
    "RTWFileNameOpts",
    "RTWMemSecFuncInitTerm",
    "RTWMemSecFuncExecute",
    "ActiveVariant",
    "ActiveVariantBlock",
    "AllowZeroVariantControls",
    "BlockChoice",
    "FunctionInterfaceSpec",
    "FunctionWithSeparateData",
    "GeneratePreprocessorConditionals",
    "IsSubsystemVirtual",
    "LabelModeActiveChoice",
    "MemberBlocks",
    "PropExecContextOutsideSubsystem",
    "PropagateVariantConditions",
    "RTWFcnName",
    "RTWFileName",
    "RTWMemSecDataConstants",
    "RTWMemSecDataInternal",
    "RTWMemSecDataParameters",
    "TemplateBlock",
    "Variant",
    "VariantControl",
    "VariantControlMode"
   ],
   "values":[
    "FromPortIcon",
    "ReadWrite",
    "",
    "All",
    "off",
    "off",
    "-1",
    "on",
    "Auto",
    "Auto",
    "Auto",
    "Inherit from model",
    "Inherit from model",
    "",
    "",
    "off",
    "",
    "void_void",
    "off",
    "off",
    "on",
    "",
    "",
    "off",
    "off",
    "",
    "",
    "Inherit from model",
    "Inherit from model",
    "Inherit from model",
    "",
    "off",
    "",
    "Expression"
   ],
   "tabs":[
    "Main",
    "Code Generation",
    "-Other"
   ],
   "tabs_idx":[
    0,
    8,
    13
   ]
  },
  "viewer":{
   "jshandler":"webview/handlers/ContainerHandler"
  },
  "obj_viewer":[
  ],
  "finder":{
   "blocktype":"SubSystem",
   "masktype":""
  }
 },
 {
  "sid":"Main_Sim:593:76:1:92:60",
  "className":"Simulink.SubSystem",
  "icon":"WebViewIcon1",
  "name":"Subsystem3",
  "label":"Subsystem3",
  "parent":"Main_Sim:593:76:1:92:36",
  "inspector":{
   "params":[
    "ShowPortLabels",
    "Permissions",
    "ErrorFcn",
    "PermitHierarchicalResolution",
    "TreatAsAtomicUnit",
    "MinAlgLoopOccurrences",
    "SystemSampleTime",
    "TreatAsGroupedWhenPropagatingVariantConditions",
    "RTWSystemCode",
    "RTWFcnNameOpts",
    "RTWFileNameOpts",
    "RTWMemSecFuncInitTerm",
    "RTWMemSecFuncExecute",
    "ActiveVariant",
    "ActiveVariantBlock",
    "AllowZeroVariantControls",
    "BlockChoice",
    "FunctionInterfaceSpec",
    "FunctionWithSeparateData",
    "GeneratePreprocessorConditionals",
    "IsSubsystemVirtual",
    "LabelModeActiveChoice",
    "MemberBlocks",
    "PropExecContextOutsideSubsystem",
    "PropagateVariantConditions",
    "RTWFcnName",
    "RTWFileName",
    "RTWMemSecDataConstants",
    "RTWMemSecDataInternal",
    "RTWMemSecDataParameters",
    "TemplateBlock",
    "Variant",
    "VariantControl",
    "VariantControlMode"
   ],
   "values":[
    "FromPortIcon",
    "ReadWrite",
    "",
    "All",
    "off",
    "off",
    "-1",
    "on",
    "Auto",
    "Auto",
    "Auto",
    "Inherit from model",
    "Inherit from model",
    "",
    "",
    "off",
    "",
    "void_void",
    "off",
    "off",
    "on",
    "",
    "",
    "off",
    "off",
    "",
    "",
    "Inherit from model",
    "Inherit from model",
    "Inherit from model",
    "",
    "off",
    "",
    "Expression"
   ],
   "tabs":[
    "Main",
    "Code Generation",
    "-Other"
   ],
   "tabs_idx":[
    0,
    8,
    13
   ]
  },
  "viewer":{
   "jshandler":"webview/handlers/ContainerHandler"
  },
  "obj_viewer":[
  ],
  "finder":{
   "blocktype":"SubSystem",
   "masktype":""
  }
 },
 {
  "sid":"Main_Sim:593:76:1:92:45",
  "className":"Simulink.SubSystem",
  "icon":"WebViewIcon1",
  "name":"Subsystem2",
  "label":"Subsystem2",
  "parent":"Main_Sim:593:76:1:92:36",
  "inspector":{
   "params":[
    "ShowPortLabels",
    "Permissions",
    "ErrorFcn",
    "PermitHierarchicalResolution",
    "TreatAsAtomicUnit",
    "MinAlgLoopOccurrences",
    "SystemSampleTime",
    "TreatAsGroupedWhenPropagatingVariantConditions",
    "RTWSystemCode",
    "RTWFcnNameOpts",
    "RTWFileNameOpts",
    "RTWMemSecFuncInitTerm",
    "RTWMemSecFuncExecute",
    "ActiveVariant",
    "ActiveVariantBlock",
    "AllowZeroVariantControls",
    "BlockChoice",
    "FunctionInterfaceSpec",
    "FunctionWithSeparateData",
    "GeneratePreprocessorConditionals",
    "IsSubsystemVirtual",
    "LabelModeActiveChoice",
    "MemberBlocks",
    "PropExecContextOutsideSubsystem",
    "PropagateVariantConditions",
    "RTWFcnName",
    "RTWFileName",
    "RTWMemSecDataConstants",
    "RTWMemSecDataInternal",
    "RTWMemSecDataParameters",
    "TemplateBlock",
    "Variant",
    "VariantControl",
    "VariantControlMode"
   ],
   "values":[
    "FromPortIcon",
    "ReadWrite",
    "",
    "All",
    "off",
    "off",
    "-1",
    "on",
    "Auto",
    "Auto",
    "Auto",
    "Inherit from model",
    "Inherit from model",
    "",
    "",
    "off",
    "",
    "void_void",
    "off",
    "off",
    "on",
    "",
    "",
    "off",
    "off",
    "",
    "",
    "Inherit from model",
    "Inherit from model",
    "Inherit from model",
    "",
    "off",
    "",
    "Expression"
   ],
   "tabs":[
    "Main",
    "Code Generation",
    "-Other"
   ],
   "tabs_idx":[
    0,
    8,
    13
   ]
  },
  "viewer":{
   "jshandler":"webview/handlers/ContainerHandler"
  },
  "obj_viewer":[
  ],
  "finder":{
   "blocktype":"SubSystem",
   "masktype":""
  }
 },
 {
  "sid":"Main_Sim:593:76:1:92:44",
  "className":"Simulink.RelationalOperator",
  "icon":"WebViewIcon3",
  "name":"Relational Operator",
  "label":"Relational Operator",
  "parent":"Main_Sim:593:76:1:92:36",
  "inspector":{
   "params":[
    "Operator",
    "ZeroCross",
    "InputSameDT",
    "OutDataTypeStr",
    "RndMeth",
    "SampleTime"
   ],
   "values":[
    "~=",
    "on",
    "off",
    "boolean",
    "Nearest",
    "-1"
   ],
   "tabs":[
    "Main",
    "Data Type",
    "-Other"
   ],
   "tabs_idx":[
    0,
    2,
    5
   ]
  },
  "viewer":{
   "jshandler":"webview/handlers/ElementHandler"
  },
  "obj_viewer":[
  ],
  "finder":{
   "blocktype":"RelationalOperator",
   "masktype":""
  }
 },
 {
  "sid":"Main_Sim:593:76:1:92:43",
  "className":"Simulink.InportShadow",
  "icon":"WebViewIcon3",
  "name":"1-f ",
  "label":"1-f ",
  "parent":"Main_Sim:593:76:1:92:36",
  "inspector":{
   "params":[
    "Port",
    "IconDisplay",
    "LatchByDelayingOutsideSignal",
    "LatchInputForFeedbackSignals",
    "OutputFunctionCall",
    "OutMin",
    "OutMax",
    "OutDataTypeStr",
    "LockScale",
    "Unit",
    "PortDimensions",
    "VarSizeSig",
    "SampleTime",
    "SignalType",
    "BusOutputAsStruct",
    "Element",
    "InputConnect",
    "Interpolate",
    "IsBusElementPort",
    "PortName"
   ],
   "values":[
    "4",
    "Port number",
    "off",
    "off",
    "off",
    "[]",
    "[]",
    "Inherit: auto",
    "off",
    "inherit",
    "-1",
    "Inherit",
    "-1",
    "auto",
    "off",
    "",
    "",
    "on",
    "off",
    "1-f"
   ],
   "tabs":[
    "Main",
    "Signal Attributes",
    "-Other"
   ],
   "tabs_idx":[
    0,
    4,
    14
   ]
  },
  "viewer":{
   "jshandler":"webview/handlers/ElementHandler"
  },
  "obj_viewer":[
  ],
  "finder":{
   "blocktype":"InportShadow",
   "masktype":""
  }
 },
 {
  "sid":"Main_Sim:593:76:1:92:42",
  "className":"Simulink.Inport",
  "icon":"WebViewIcon3",
  "name":"ep2",
  "label":"ep2",
  "parent":"Main_Sim:593:76:1:92:36",
  "inspector":{
   "params":[
    "Port",
    "IconDisplay",
    "LatchByDelayingOutsideSignal",
    "LatchInputForFeedbackSignals",
    "OutputFunctionCall",
    "OutMin",
    "OutMax",
    "OutDataTypeStr",
    "LockScale",
    "Unit",
    "PortDimensions",
    "VarSizeSig",
    "SampleTime",
    "SignalType",
    "BusOutputAsStruct",
    "InputConnect",
    "Interpolate"
   ],
   "values":[
    "6",
    "Port number",
    "off",
    "off",
    "off",
    "[]",
    "[]",
    "Inherit: auto",
    "off",
    "inherit",
    "-1",
    "Inherit",
    "-1",
    "auto",
    "off",
    "",
    "on"
   ],
   "tabs":[
    "Main",
    "Signal Attributes",
    "-Other"
   ],
   "tabs_idx":[
    0,
    4,
    14
   ]
  },
  "viewer":{
   "jshandler":"webview/handlers/ElementHandler"
  },
  "obj_viewer":[
  ],
  "finder":{
   "blocktype":"Inport",
   "masktype":""
  }
 },
 {
  "sid":"Main_Sim:593:76:1:92:41",
  "className":"Simulink.Inport",
  "icon":"WebViewIcon3",
  "name":"e2",
  "label":"e2",
  "parent":"Main_Sim:593:76:1:92:36",
  "inspector":{
   "params":[
    "Port",
    "IconDisplay",
    "LatchByDelayingOutsideSignal",
    "LatchInputForFeedbackSignals",
    "OutputFunctionCall",
    "OutMin",
    "OutMax",
    "OutDataTypeStr",
    "LockScale",
    "Unit",
    "PortDimensions",
    "VarSizeSig",
    "SampleTime",
    "SignalType",
    "BusOutputAsStruct",
    "InputConnect",
    "Interpolate"
   ],
   "values":[
    "5",
    "Port number",
    "off",
    "off",
    "off",
    "[]",
    "[]",
    "Inherit: auto",
    "off",
    "inherit",
    "-1",
    "Inherit",
    "-1",
    "auto",
    "off",
    "",
    "on"
   ],
   "tabs":[
    "Main",
    "Signal Attributes",
    "-Other"
   ],
   "tabs_idx":[
    0,
    4,
    14
   ]
  },
  "viewer":{
   "jshandler":"webview/handlers/ElementHandler"
  },
  "obj_viewer":[
  ],
  "finder":{
   "blocktype":"Inport",
   "masktype":""
  }
 },
 {
  "sid":"Main_Sim:593:76:1:92:40",
  "className":"Simulink.Inport",
  "icon":"WebViewIcon3",
  "name":"1-f",
  "label":"1-f",
  "parent":"Main_Sim:593:76:1:92:36",
  "inspector":{
   "params":[
    "Port",
    "IconDisplay",
    "LatchByDelayingOutsideSignal",
    "LatchInputForFeedbackSignals",
    "OutputFunctionCall",
    "OutMin",
    "OutMax",
    "OutDataTypeStr",
    "LockScale",
    "Unit",
    "PortDimensions",
    "VarSizeSig",
    "SampleTime",
    "SignalType",
    "BusOutputAsStruct",
    "InputConnect",
    "Interpolate"
   ],
   "values":[
    "4",
    "Port number",
    "off",
    "off",
    "off",
    "[]",
    "[]",
    "Inherit: auto",
    "off",
    "inherit",
    "-1",
    "Inherit",
    "-1",
    "auto",
    "off",
    "",
    "on"
   ],
   "tabs":[
    "Main",
    "Signal Attributes",
    "-Other"
   ],
   "tabs_idx":[
    0,
    4,
    14
   ]
  },
  "viewer":{
   "jshandler":"webview/handlers/ElementHandler"
  },
  "obj_viewer":[
  ],
  "finder":{
   "blocktype":"Inport",
   "masktype":""
  }
 },
 {
  "sid":"Main_Sim:593:76:1:92:39",
  "className":"Simulink.Inport",
  "icon":"WebViewIcon3",
  "name":"b",
  "label":"b",
  "parent":"Main_Sim:593:76:1:92:36",
  "inspector":{
   "params":[
    "Port",
    "IconDisplay",
    "LatchByDelayingOutsideSignal",
    "LatchInputForFeedbackSignals",
    "OutputFunctionCall",
    "OutMin",
    "OutMax",
    "OutDataTypeStr",
    "LockScale",
    "Unit",
    "PortDimensions",
    "VarSizeSig",
    "SampleTime",
    "SignalType",
    "BusOutputAsStruct",
    "InputConnect",
    "Interpolate"
   ],
   "values":[
    "3",
    "Port number",
    "off",
    "off",
    "off",
    "[]",
    "[]",
    "Inherit: auto",
    "off",
    "inherit",
    "-1",
    "Inherit",
    "-1",
    "auto",
    "off",
    "",
    "on"
   ],
   "tabs":[
    "Main",
    "Signal Attributes",
    "-Other"
   ],
   "tabs_idx":[
    0,
    4,
    14
   ]
  },
  "viewer":{
   "jshandler":"webview/handlers/ElementHandler"
  },
  "obj_viewer":[
  ],
  "finder":{
   "blocktype":"Inport",
   "masktype":""
  }
 },
 {
  "sid":"Main_Sim:593:76:1:92:38",
  "className":"Simulink.Inport",
  "icon":"WebViewIcon3",
  "name":"z",
  "label":"z",
  "parent":"Main_Sim:593:76:1:92:36",
  "inspector":{
   "params":[
    "Port",
    "IconDisplay",
    "LatchByDelayingOutsideSignal",
    "LatchInputForFeedbackSignals",
    "OutputFunctionCall",
    "OutMin",
    "OutMax",
    "OutDataTypeStr",
    "LockScale",
    "Unit",
    "PortDimensions",
    "VarSizeSig",
    "SampleTime",
    "SignalType",
    "BusOutputAsStruct",
    "InputConnect",
    "Interpolate"
   ],
   "values":[
    "2",
    "Port number",
    "off",
    "off",
    "off",
    "[]",
    "[]",
    "Inherit: auto",
    "off",
    "inherit",
    "-1",
    "Inherit",
    "-1",
    "auto",
    "off",
    "",
    "on"
   ],
   "tabs":[
    "Main",
    "Signal Attributes",
    "-Other"
   ],
   "tabs_idx":[
    0,
    4,
    14
   ]
  },
  "viewer":{
   "jshandler":"webview/handlers/ElementHandler"
  },
  "obj_viewer":[
  ],
  "finder":{
   "blocktype":"Inport",
   "masktype":""
  }
 },
 {
  "sid":"Main_Sim:593:76:1:92:37",
  "className":"Simulink.Inport",
  "icon":"WebViewIcon3",
  "name":"rho",
  "label":"rho",
  "parent":"Main_Sim:593:76:1:92:36",
  "inspector":{
   "params":[
    "Port",
    "IconDisplay",
    "LatchByDelayingOutsideSignal",
    "LatchInputForFeedbackSignals",
    "OutputFunctionCall",
    "OutMin",
    "OutMax",
    "OutDataTypeStr",
    "LockScale",
    "Unit",
    "PortDimensions",
    "VarSizeSig",
    "SampleTime",
    "SignalType",
    "BusOutputAsStruct",
    "InputConnect",
    "Interpolate"
   ],
   "values":[
    "1",
    "Port number",
    "off",
    "off",
    "off",
    "[]",
    "[]",
    "Inherit: auto",
    "off",
    "inherit",
    "-1",
    "Inherit",
    "-1",
    "auto",
    "off",
    "",
    "on"
   ],
   "tabs":[
    "Main",
    "Signal Attributes",
    "-Other"
   ],
   "tabs_idx":[
    0,
    4,
    14
   ]
  },
  "viewer":{
   "jshandler":"webview/handlers/ElementHandler"
  },
  "obj_viewer":[
  ],
  "finder":{
   "blocktype":"Inport",
   "masktype":""
  }
 },
 {
  "sid":"Main_Sim:593:76:1:92:60#out:1",
  "className":"Simulink.Line",
  "icon":"WebViewIcon5",
  "name":"",
  "label":"",
  "parent":"Main_Sim:593:76:1:92:36",
  "inspector":{
   "params":[
    "SignalNameFromLabel",
    "MustResolveToSignal",
    "ShowPropagatedSignal",
    "DataLogging",
    "TestPoint",
    "SignalObjectPackage",
    "StorageClass",
    "Description",
    "documentLink"
   ],
   "values":[
    "",
    "off",
    "off",
    "off",
    "off",
    "Simulink",
    "Auto",
    "",
    ""
   ],
   "tabs":[
    "Parameter Attributes",
    "Logging and Accessibility",
    "Code Generation",
    "Documentation"
   ],
   "tabs_idx":[
    0,
    3,
    5,
    7
   ]
  },
  "viewer":{
   "jshandler":"webview/handlers/ElementHandler"
  },
  "obj_viewer":[
  ],
  "finder":[
  ]
 },
 {
  "sid":"Main_Sim:593:76:1:92:78#out:1",
  "className":"Simulink.Line",
  "icon":"WebViewIcon5",
  "name":"",
  "label":"",
  "parent":"Main_Sim:593:76:1:92:36",
  "inspector":{
   "params":[
    "SignalNameFromLabel",
    "MustResolveToSignal",
    "ShowPropagatedSignal",
    "DataLogging",
    "TestPoint",
    "SignalObjectPackage",
    "StorageClass",
    "Description",
    "documentLink"
   ],
   "values":[
    "",
    "off",
    "off",
    "off",
    "off",
    "Simulink",
    "Auto",
    "",
    ""
   ],
   "tabs":[
    "Parameter Attributes",
    "Logging and Accessibility",
    "Code Generation",
    "Documentation"
   ],
   "tabs_idx":[
    0,
    3,
    5,
    7
   ]
  },
  "viewer":{
   "jshandler":"webview/handlers/ElementHandler"
  },
  "obj_viewer":[
  ],
  "finder":[
  ]
 },
 {
  "sid":"Main_Sim:593:76:1:92:43#out:1",
  "className":"Simulink.Line",
  "icon":"WebViewIcon5",
  "name":"",
  "label":"",
  "parent":"Main_Sim:593:76:1:92:36",
  "inspector":{
   "params":[
    "SignalNameFromLabel",
    "MustResolveToSignal",
    "ShowPropagatedSignal",
    "DataLogging",
    "TestPoint",
    "SignalObjectPackage",
    "StorageClass",
    "Description",
    "documentLink"
   ],
   "values":[
    "",
    "off",
    "off",
    "off",
    "off",
    "Simulink",
    "Auto",
    "",
    ""
   ],
   "tabs":[
    "Parameter Attributes",
    "Logging and Accessibility",
    "Code Generation",
    "Documentation"
   ],
   "tabs_idx":[
    0,
    3,
    5,
    7
   ]
  },
  "viewer":{
   "jshandler":"webview/handlers/ElementHandler"
  },
  "obj_viewer":[
  ],
  "finder":[
  ]
 },
 {
  "sid":"Main_Sim:593:76:1:92:40#out:1",
  "className":"Simulink.Line",
  "icon":"WebViewIcon5",
  "name":"",
  "label":"",
  "parent":"Main_Sim:593:76:1:92:36",
  "inspector":{
   "params":[
    "SignalNameFromLabel",
    "MustResolveToSignal",
    "ShowPropagatedSignal",
    "DataLogging",
    "TestPoint",
    "SignalObjectPackage",
    "StorageClass",
    "Description",
    "documentLink"
   ],
   "values":[
    "",
    "off",
    "off",
    "off",
    "off",
    "Simulink",
    "Auto",
    "",
    ""
   ],
   "tabs":[
    "Parameter Attributes",
    "Logging and Accessibility",
    "Code Generation",
    "Documentation"
   ],
   "tabs_idx":[
    0,
    3,
    5,
    7
   ]
  },
  "viewer":{
   "jshandler":"webview/handlers/ElementHandler"
  },
  "obj_viewer":[
  ],
  "finder":[
  ]
 },
 {
  "sid":"Main_Sim:593:76:1:92:41#out:1",
  "className":"Simulink.Line",
  "icon":"WebViewIcon5",
  "name":"",
  "label":"",
  "parent":"Main_Sim:593:76:1:92:36",
  "inspector":{
   "params":[
    "SignalNameFromLabel",
    "MustResolveToSignal",
    "ShowPropagatedSignal",
    "DataLogging",
    "TestPoint",
    "SignalObjectPackage",
    "StorageClass",
    "Description",
    "documentLink"
   ],
   "values":[
    "",
    "off",
    "off",
    "off",
    "off",
    "Simulink",
    "Auto",
    "",
    ""
   ],
   "tabs":[
    "Parameter Attributes",
    "Logging and Accessibility",
    "Code Generation",
    "Documentation"
   ],
   "tabs_idx":[
    0,
    3,
    5,
    7
   ]
  },
  "viewer":{
   "jshandler":"webview/handlers/ElementHandler"
  },
  "obj_viewer":[
  ],
  "finder":[
  ]
 },
 {
  "sid":"Main_Sim:593:76:1:92:39#out:1",
  "className":"Simulink.Line",
  "icon":"WebViewIcon5",
  "name":"",
  "label":"",
  "parent":"Main_Sim:593:76:1:92:36",
  "inspector":{
   "params":[
    "SignalNameFromLabel",
    "MustResolveToSignal",
    "ShowPropagatedSignal",
    "DataLogging",
    "TestPoint",
    "SignalObjectPackage",
    "StorageClass",
    "Description",
    "documentLink"
   ],
   "values":[
    "",
    "off",
    "off",
    "off",
    "off",
    "Simulink",
    "Auto",
    "",
    ""
   ],
   "tabs":[
    "Parameter Attributes",
    "Logging and Accessibility",
    "Code Generation",
    "Documentation"
   ],
   "tabs_idx":[
    0,
    3,
    5,
    7
   ]
  },
  "viewer":{
   "jshandler":"webview/handlers/ElementHandler"
  },
  "obj_viewer":[
  ],
  "finder":[
  ]
 },
 {
  "sid":"Main_Sim:593:76:1:92:44#out:1",
  "className":"Simulink.Line",
  "icon":"WebViewIcon5",
  "name":"",
  "label":"",
  "parent":"Main_Sim:593:76:1:92:36",
  "inspector":{
   "params":[
    "SignalNameFromLabel",
    "MustResolveToSignal",
    "ShowPropagatedSignal",
    "DataLogging",
    "TestPoint",
    "SignalObjectPackage",
    "StorageClass",
    "Description",
    "documentLink"
   ],
   "values":[
    "",
    "off",
    "off",
    "off",
    "off",
    "Simulink",
    "Auto",
    "",
    ""
   ],
   "tabs":[
    "Parameter Attributes",
    "Logging and Accessibility",
    "Code Generation",
    "Documentation"
   ],
   "tabs_idx":[
    0,
    3,
    5,
    7
   ]
  },
  "viewer":{
   "jshandler":"webview/handlers/ElementHandler"
  },
  "obj_viewer":[
  ],
  "finder":[
  ]
 },
 {
  "sid":"Main_Sim:593:76:1:92:38#out:1",
  "className":"Simulink.Line",
  "icon":"WebViewIcon5",
  "name":"",
  "label":"",
  "parent":"Main_Sim:593:76:1:92:36",
  "inspector":{
   "params":[
    "SignalNameFromLabel",
    "MustResolveToSignal",
    "ShowPropagatedSignal",
    "DataLogging",
    "TestPoint",
    "SignalObjectPackage",
    "StorageClass",
    "Description",
    "documentLink"
   ],
   "values":[
    "",
    "off",
    "off",
    "off",
    "off",
    "Simulink",
    "Auto",
    "",
    ""
   ],
   "tabs":[
    "Parameter Attributes",
    "Logging and Accessibility",
    "Code Generation",
    "Documentation"
   ],
   "tabs_idx":[
    0,
    3,
    5,
    7
   ]
  },
  "viewer":{
   "jshandler":"webview/handlers/ElementHandler"
  },
  "obj_viewer":[
  ],
  "finder":[
  ]
 },
 {
  "sid":"Main_Sim:593:76:1:92:45#out:1",
  "className":"Simulink.Line",
  "icon":"WebViewIcon5",
  "name":"",
  "label":"",
  "parent":"Main_Sim:593:76:1:92:36",
  "inspector":{
   "params":[
    "SignalNameFromLabel",
    "MustResolveToSignal",
    "ShowPropagatedSignal",
    "DataLogging",
    "TestPoint",
    "SignalObjectPackage",
    "StorageClass",
    "Description",
    "documentLink"
   ],
   "values":[
    "",
    "off",
    "off",
    "off",
    "off",
    "Simulink",
    "Auto",
    "",
    ""
   ],
   "tabs":[
    "Parameter Attributes",
    "Logging and Accessibility",
    "Code Generation",
    "Documentation"
   ],
   "tabs_idx":[
    0,
    3,
    5,
    7
   ]
  },
  "viewer":{
   "jshandler":"webview/handlers/ElementHandler"
  },
  "obj_viewer":[
  ],
  "finder":[
  ]
 },
 {
  "sid":"Main_Sim:593:76:1:92:67#out:1",
  "className":"Simulink.Line",
  "icon":"WebViewIcon5",
  "name":"",
  "label":"",
  "parent":"Main_Sim:593:76:1:92:36",
  "inspector":{
   "params":[
    "SignalNameFromLabel",
    "MustResolveToSignal",
    "ShowPropagatedSignal",
    "DataLogging",
    "TestPoint",
    "SignalObjectPackage",
    "StorageClass",
    "Description",
    "documentLink"
   ],
   "values":[
    "",
    "off",
    "off",
    "off",
    "off",
    "Simulink",
    "Auto",
    "",
    ""
   ],
   "tabs":[
    "Parameter Attributes",
    "Logging and Accessibility",
    "Code Generation",
    "Documentation"
   ],
   "tabs_idx":[
    0,
    3,
    5,
    7
   ]
  },
  "viewer":{
   "jshandler":"webview/handlers/ElementHandler"
  },
  "obj_viewer":[
  ],
  "finder":[
  ]
 },
 {
  "sid":"Main_Sim:593:76:1:92:42#out:1",
  "className":"Simulink.Line",
  "icon":"WebViewIcon5",
  "name":"",
  "label":"",
  "parent":"Main_Sim:593:76:1:92:36",
  "inspector":{
   "params":[
    "SignalNameFromLabel",
    "MustResolveToSignal",
    "ShowPropagatedSignal",
    "DataLogging",
    "TestPoint",
    "SignalObjectPackage",
    "StorageClass",
    "Description",
    "documentLink"
   ],
   "values":[
    "",
    "off",
    "off",
    "off",
    "off",
    "Simulink",
    "Auto",
    "",
    ""
   ],
   "tabs":[
    "Parameter Attributes",
    "Logging and Accessibility",
    "Code Generation",
    "Documentation"
   ],
   "tabs_idx":[
    0,
    3,
    5,
    7
   ]
  },
  "viewer":{
   "jshandler":"webview/handlers/ElementHandler"
  },
  "obj_viewer":[
  ],
  "finder":[
  ]
 },
 {
  "sid":"Main_Sim:593:76:1:92:37#out:1",
  "className":"Simulink.Line",
  "icon":"WebViewIcon5",
  "name":"",
  "label":"",
  "parent":"Main_Sim:593:76:1:92:36",
  "inspector":{
   "params":[
    "SignalNameFromLabel",
    "MustResolveToSignal",
    "ShowPropagatedSignal",
    "DataLogging",
    "TestPoint",
    "SignalObjectPackage",
    "StorageClass",
    "Description",
    "documentLink"
   ],
   "values":[
    "",
    "off",
    "off",
    "off",
    "off",
    "Simulink",
    "Auto",
    "",
    ""
   ],
   "tabs":[
    "Parameter Attributes",
    "Logging and Accessibility",
    "Code Generation",
    "Documentation"
   ],
   "tabs_idx":[
    0,
    3,
    5,
    7
   ]
  },
  "viewer":{
   "jshandler":"webview/handlers/ElementHandler"
  },
  "obj_viewer":[
  ],
  "finder":[
  ]
 },
 {
  "sid":"Main_Sim:593:76:1:92:79#out:1",
  "className":"Simulink.Line",
  "icon":"WebViewIcon5",
  "name":"",
  "label":"",
  "parent":"Main_Sim:593:76:1:92:36",
  "inspector":{
   "params":[
    "SignalNameFromLabel",
    "MustResolveToSignal",
    "ShowPropagatedSignal",
    "DataLogging",
    "TestPoint",
    "SignalObjectPackage",
    "StorageClass",
    "Description",
    "documentLink"
   ],
   "values":[
    "",
    "off",
    "off",
    "off",
    "off",
    "Simulink",
    "Auto",
    "",
    ""
   ],
   "tabs":[
    "Parameter Attributes",
    "Logging and Accessibility",
    "Code Generation",
    "Documentation"
   ],
   "tabs_idx":[
    0,
    3,
    5,
    7
   ]
  },
  "viewer":{
   "jshandler":"webview/handlers/ElementHandler"
  },
  "obj_viewer":[
  ],
  "finder":[
  ]
 }
]